routing_transformer/__init__.py
routing_transformer/autopadder.py
routing_transformer/autoregressive_wrapper.py
routing_transformer/encoder_decoder.py
routing_transformer/reversible.py
routing_transformer/routing_transformer.py
routing_transformer-1.6.1.dist-info/LICENSE
routing_transformer-1.6.1.dist-info/METADATA
routing_transformer-1.6.1.dist-info/WHEEL
routing_transformer-1.6.1.dist-info/top_level.txt
routing_transformer-1.6.1.dist-info/RECORD
