Metadata-Version: 2.1
Name: routing-transformer
Version: 1.6.1
Summary: Routing Transformer (Pytorch)
Home-page: https://github.com/lucidrains/routing-transformer
Author: Phil Wang, Aran Komatsuzaki
Author-email: lucidrains@gmail.com, aran1234321@gmail.com
License: MIT
Keywords: transformers,attention,artificial intelligence
Platform: UNKNOWN
Classifier: Development Status :: 4 - Beta
Classifier: Intended Audience :: Developers
Classifier: Topic :: Scientific/Engineering :: Artificial Intelligence
Classifier: License :: OSI Approved :: MIT License
Classifier: Programming Language :: Python :: 3.6
License-File: LICENSE
Requires-Dist: einops
Requires-Dist: local-attention (>=1.4.0)
Requires-Dist: mixture-of-experts (>=0.2.0)
Requires-Dist: product-key-memory
Requires-Dist: torch
